polaroids/__init__.py
polaroids/_parse_types.py
polaroids/_utils.py
polaroids/dataframe.py
polaroids/dataframe.pyi
polaroids/exceptions.py
polaroids/field.py
polaroids/types.py
polaroids-0.3.0.dist-info/METADATA
polaroids-0.3.0.dist-info/WHEEL
polaroids-0.3.0.dist-info/RECORD
