Metadata-Version: 2.4
Name: polaroids
Version: 0.3.0
Summary: Validate you Generic polars dataframes
Author-email: gabriel <106454081+gab23r@users.noreply.github.com>
Requires-Python: >=3.11
Requires-Dist: polars>=1.0
